[
    {
        "x": -1457,
        "y": 138,
        "z": 126
    },
    {
        "x": -1408,
        "y": 159,
        "z": 68
    },
    {
        "x": -1441,
        "y": 180,
        "z": 92
    },
    {
        "x": -1476,
        "y": 221,
        "z": 138
    },
    {
        "x": -1451,
        "y": 170,
        "z": 95
    },
    {
        "x": -1501,
        "y": 191,
        "z": 74
    },
    {
        "x": -1456,
        "y": 173,
        "z": 143
    },
    {
        "x": -1394,
        "y": 179,
        "z": 149
    },
    {
        "x": -1475,
        "y": 181,
        "z": 108
    },
    {
        "x": -1381,
        "y": 181,
        "z": 142
    },
    {
        "x": -1495,
        "y": 159,
        "z": 111
    },
    {
        "x": -1461,
        "y": 144,
        "z": 94
    },
    {
        "x": -1412,
        "y": 153,
        "z": 85
    },
    {
        "x": -1329,
        "y": 157,
        "z": 141
    },
    {
        "x": -1379,
        "y": 88,
        "z": 92
    },
    {
        "x": -1491,
        "y": 213,
        "z": 107
    },
    {
        "x": -1359,
        "y": 190,
        "z": 47
    },
    {
        "x": -1380,
        "y": 213,
        "z": 123
    },
    {
        "x": -1463,
        "y": 149,
        "z": 141
    },
    {
        "x": -1497,
        "y": 185,
        "z": 22
    },
    {
        "x": -1419,
        "y": 159,
        "z": 112
    },
    {
        "x": -1443,
        "y": 117,
        "z": 97
    },
    {
        "x": -1386,
        "y": 179,
        "z": 39
    },
    {
        "x": -1411,
        "y": 118,
        "z": 35
    },
    {
        "x": -1453,
        "y": 211,
        "z": 15
    },
    {
        "x": -1514,
        "y": 192,
        "z": 88
    },
    {
        "x": -1424,
        "y": 163,
        "z": 134
    },
    {
        "x": -1389,
        "y": 171,
        "z": 106
    },
    {
        "x": -1457,
        "y": 189,
        "z": 136
    },
    {
        "x": -1453,
        "y": 50,
        "z": 88
    },
    {
        "x": -1502,
        "y": 176,
        "z": 70
    },
    {
        "x": -1403,
        "y": 188,
        "z": 114
    },
    {
        "x": -1393,
        "y": 161,
        "z": 109
    },
    {
        "x": -1455,
        "y": 124,
        "z": 104
    },
    {
        "x": -1457,
        "y": 204,
        "z": 58
    },
    {
        "x": -1445,
        "y": 180,
        "z": 152
    },
    {
        "x": -1441,
        "y": 188,
        "z": 32
    },
    {
        "x": -1401,
        "y": 138,
        "z": 73
    },
    {
        "x": -1385,
        "y": 137,
        "z": 91
    },
    {
        "x": -1387,
        "y": 146,
        "z": 138
    },
    {
        "x": -1491,
        "y": 178,
        "z": 85
    },
    {
        "x": -1450,
        "y": 212,
        "z": 21
    },
    {
        "x": -1495,
        "y": 159,
        "z": 110
    },
    {
        "x": -1383,
        "y": 201,
        "z": 106
    },
    {
        "x": -1400,
        "y": 195,
        "z": 54
    },
    {
        "x": -1446,
        "y": 148,
        "z": 152
    },
    {
        "x": -1513,
        "y": 192,
        "z": 69
    },
    {
        "x": -1381,
        "y": 88,
        "z": 91
    },
    {
        "x": -1388,
        "y": 179,
        "z": 95
    },
    {
        "x": -1359,
        "y": 190,
        "z": 46
    },
    {
        "x": -1463,
        "y": 149,
        "z": 140
    },
    {
        "x": -1363,
        "y": 208,
        "z": 132
    },
    {
        "x": -1497,
        "y": 185,
        "z": 23
    },
    {
        "x": -1349,
        "y": 182,
        "z": 97
    },
    {
        "x": -1429,
        "y": 191,
        "z": 33
    },
    {
        "x": -1428,
        "y": 191,
        "z": 33
    },
    {
        "x": -1411,
        "y": 152,
        "z": 136
    },
    {
        "x": -1511,
        "y": 177,
        "z": 41
    },
    {
        "x": -1398,
        "y": 117,
        "z": 60
    },
    {
        "x": -1425,
        "y": 124,
        "z": 128
    },
    {
        "x": -1443,
        "y": 224,
        "z": 57
    },
    {
        "x": -1440,
        "y": 125,
        "z": 55
    },
    {
        "x": -1457,
        "y": 204,
        "z": 57
    },
    {
        "x": -1393,
        "y": 161,
        "z": 110
    },
    {
        "x": -1455,
        "y": 124,
        "z": 103
    },
    {
        "x": -1412,
        "y": 153,
        "z": 59
    }
]